ses_mail/__init__.py
ses_mail/send_ses.py
ses_email_service-0.1.dist-info/LICENSE
ses_email_service-0.1.dist-info/METADATA
ses_email_service-0.1.dist-info/WHEEL
ses_email_service-0.1.dist-info/top_level.txt
ses_email_service-0.1.dist-info/RECORD
