Metadata-Version: 2.1
Name: ses_email_service
Version: 0.1
Summary: A Python library for sending emails with the help of amazon service SES (simple email service).
Author-email: Harshit Bhalla <harshit.bhalla.002@gmail.com>
Project-URL: Homepage, https://github.com/HarshitNci/ses-library
Classifier: Programming Language :: Python :: 3
Classifier: License :: OSI Approved :: MIT License
Classifier: Operating System :: OS Independent
Requires-Python: >=3.8
License-File: LICENSE
